imgb64/__init__.py
imgb64/imgb64.py
imgb64-2.7.1.1.dist-info/METADATA
imgb64-2.7.1.1.dist-info/WHEEL
imgb64-2.7.1.1.dist-info/top_level.txt
imgb64-2.7.1.1.dist-info/RECORD
