Metadata-Version: 2.4
Name: imgb64
Version: 2.7.1.1
Summary: Base64 image encode/decode
Author: Wl13Proger9
Requires-Python: >=3.8
